pada/__init__.py
pada/cli.py
pada/templating.py
pada/assemble/__init__.py
pada/assemble/assembles.py
pada/assemble/hooks.py
pada/assemble/locates.py
pada/assemble/pipes.py
pada/assemble/runner.py
pada/assemble/settings.py
pada/assemble/visit.py
pada/check/__init__.py
pada/check/checks.py
pada/check/exception.py
pada/feature/__init__.py
pada/feature/datasets.py
pada/feature/features.py
pada/feature/pipeline.py
pada/feature/transformer.py
pada/libs/__init__.py
pada/libs/base.py
pada/libs/misc.py
pada/libs/missing.py
pada/libs/ts.py
pada/libs/external/__init__.py
pada/libs/external/category_encoders.py
pada/libs/external/feature_engine.py
pada/libs/external/featuretools.py
pada/libs/external/skits.py
pada/libs/external/sklearn.py
pada/libs/external/tsfresh.py
pada/templates/__init__.py
pada/utils/__init__.py
pada/utils/compat.py
pada/utils/log.py
pada/utils/state.py
pada-0.1.0.dist-info/LICENSE
pada-0.1.0.dist-info/METADATA
pada-0.1.0.dist-info/WHEEL
pada-0.1.0.dist-info/top_level.txt
pada-0.1.0.dist-info/RECORD
