Metadata-Version: 2.1
Name: pada
Version: 0.1.0
Summary: a ligthweight feature manage framework
Home-page: https://github.com/eleveyuan/pada
Author: Eleve Yuan
Author-email: eleveyuane@gmail.com
License: MIT license
Keywords: pada
Platform: UNKNOWN
Classifier: Development Status :: 4 - Beta
Classifier: Intended Audience :: Developers
Classifier: License :: OSI Approved :: MIT License
Classifier: Programming Language :: Python :: 3
Classifier: Programming Language :: Python :: 3.7
Classifier: Programming Language :: Python :: 3.8
Requires-Python: >=3.7.0
License-File: LICENSE
Requires-Dist: cookiecutter
Requires-Dist: Click (>=6.0)
Requires-Dist: funcy (>=1.14)
Requires-Dist: scikit-learn (>=0.20)
Requires-Dist: sklearn-pandas (~=1.0)
Requires-Dist: stacklog
Requires-Dist: pandas (~=1.0)
Requires-Dist: numpy
Provides-Extra: all
Requires-Dist: category-encoders (>=2.2.2) ; extra == 'all'
Requires-Dist: feature-engine (~=1.0) ; extra == 'all'
Requires-Dist: featuretools-sklearn-transformer (>=0.1) ; extra == 'all'
Requires-Dist: skits (>=0.1.2) ; extra == 'all'
Requires-Dist: tsfresh (>=0.16) ; extra == 'all'
Provides-Extra: category_encoders
Requires-Dist: category-encoders (>=2.2.2) ; extra == 'category_encoders'
Provides-Extra: feature_engine
Requires-Dist: feature-engine (~=1.0) ; extra == 'feature_engine'
Provides-Extra: featuretools
Requires-Dist: featuretools-sklearn-transformer (>=0.1) ; extra == 'featuretools'
Provides-Extra: skits
Requires-Dist: skits (>=0.1.2) ; extra == 'skits'
Provides-Extra: tsfresh
Requires-Dist: tsfresh (>=0.16) ; extra == 'tsfresh'
